asgi_proxy/__init__.py
asgi_proxy/__main__.py
asgi_proxy_lib-0.2a0.dist-info/LICENSE
asgi_proxy_lib-0.2a0.dist-info/METADATA
asgi_proxy_lib-0.2a0.dist-info/WHEEL
asgi_proxy_lib-0.2a0.dist-info/top_level.txt
asgi_proxy_lib-0.2a0.dist-info/RECORD
