Metadata-Version: 2.1
Name: asgi-proxy-lib
Version: 0.2a0
Summary: An ASGI function for proxying to a backend over HTTP
Home-page: https://github.com/simonw/asgi-proxy-lib
Author: Simon Willison
License: Apache License, Version 2.0
Project-URL: Issues, https://github.com/simonw/asgi-proxy-lib/issues
Project-URL: CI, https://github.com/simonw/asgi-proxy-lib/actions
Project-URL: Changelog, https://github.com/simonw/asgi-proxy-lib/releases
Requires-Python: >=3.9
License-File: LICENSE
Requires-Dist: httpx
Provides-Extra: test
Requires-Dist: pytest ; extra == 'test'
Requires-Dist: pytest-asyncio ; extra == 'test'
Requires-Dist: pytest-httpx ; extra == 'test'
